awkwardql/__init__.py
awkwardql/data.py
awkwardql/index.py
awkwardql/interface.py
awkwardql/interpreter.py
awkwardql/parser.py
awkwardql/version.py
awkwardql-0.0.1.dev4.dist-info/LICENSE
awkwardql-0.0.1.dev4.dist-info/METADATA
awkwardql-0.0.1.dev4.dist-info/WHEEL
awkwardql-0.0.1.dev4.dist-info/top_level.txt
awkwardql-0.0.1.dev4.dist-info/RECORD
