Metadata-Version: 2.1
Name: awkwardql
Version: 0.0.1.dev4
Summary: SQL-like language for awkward arrays
Home-page: https://github.com/lgray/AwkwardQL
Author: Lindsey Gray (Fermilab), Jim Pivarski (Princeton)
Author-email: lagray@fnal.gov
Maintainer: Lindsey Gray (Fermilab)
Maintainer-email: lagray@fnal.gov
License: BSD 3-clause
Download-URL: https://github.com/lgray/AwkwardQL/releases
Platform: Any
Classifier: Development Status :: 4 - Beta
Classifier: Intended Audience :: Developers
Classifier: Intended Audience :: Information Technology
Classifier: Intended Audience :: Science/Research
Classifier: License :: OSI Approved :: BSD License
Classifier: Operating System :: MacOS
Classifier: Operating System :: POSIX
Classifier: Operating System :: Unix
Classifier: Programming Language :: Python
Classifier: Programming Language :: Python :: 3.6
Classifier: Programming Language :: Python :: 3.7
Classifier: Programming Language :: Python :: 3.8
Classifier: Topic :: Scientific/Engineering
Classifier: Topic :: Scientific/Engineering :: Information Analysis
Classifier: Topic :: Scientific/Engineering :: Mathematics
Classifier: Topic :: Scientific/Engineering :: Physics
Classifier: Topic :: Software Development
Classifier: Topic :: Utilities
Requires-Dist: lark-parser (>=0.7.8)
Requires-Dist: awkward1 (>=0.1.84)
Requires-Dist: numba (>=0.43.1)
Requires-Dist: numpy (>=1.16.0)
Requires-Dist: matplotlib
